es_pandas/__init__.py
es_pandas/es_pandas.py
es_pandas-0.0.23.dist-info/LICENSE
es_pandas-0.0.23.dist-info/METADATA
es_pandas-0.0.23.dist-info/WHEEL
es_pandas-0.0.23.dist-info/top_level.txt
es_pandas-0.0.23.dist-info/RECORD
