Metadata-Version: 2.1
Name: es-pandas
Version: 0.0.23
Summary: Read, write and update large scale pandas DataFrame with ElasticSearch
Home-page: https://github.com/fuyb1992/es_pandas
Author: Frank
Author-email: fu.frank@foxmail.com
License: UNKNOWN
Platform: UNKNOWN
Classifier: Programming Language :: Python :: 3
Classifier: License :: OSI Approved :: MIT License
Classifier: Operating System :: OS Independent
License-File: LICENSE
Requires-Dist: pandas
Requires-Dist: elasticsearch
Requires-Dist: tqdm
Requires-Dist: requests
